craft2d/__init__.py
craft2d/config/__init__.py
craft2d/env/__init__.py
craft2d/env/environment.py
craft2d/render/__init__.py
craft2d/render/render.py
craft2d/resources/agent/agent-down.png
craft2d/resources/agent/agent-left.png
craft2d/resources/agent/agent-right.png
craft2d/resources/agent/agent-up.png
craft2d/resources/farm/plant-large.png
craft2d/resources/farm/plant-medium.png
craft2d/resources/farm/plant-small.png
craft2d/resources/objects/bridge.png
craft2d/resources/objects/crafting-table.png
craft2d/resources/objects/gem.png
craft2d/resources/objects/grass.png
craft2d/resources/objects/princess.png
craft2d/resources/objects/rope.png
craft2d/resources/objects/sticks.png
craft2d/resources/objects/stone.png
craft2d/resources/objects/tree.png
craft2d/resources/objects/weapon-advanced.png
craft2d/resources/objects/weapon-basic.png
craft2d/resources/objects/wood.png
craft2d/resources/terrain/grass.png
craft2d/resources/terrain/island.png
craft2d/resources/terrain/water.png
craft2d-0.1.9.dist-info/METADATA
craft2d-0.1.9.dist-info/WHEEL
craft2d-0.1.9.dist-info/RECORD
