Metadata-Version: 2.1
Name: craft2d
Version: 0.1.9
Summary: 
Author: Tristan Bester
Author-email: tristanbester@gmail.com
Requires-Python: >=3.9,<4.0
Classifier: Programming Language :: Python :: 3
Classifier: Programming Language :: Python :: 3.9
Classifier: Programming Language :: Python :: 3.10
Classifier: Programming Language :: Python :: 3.11
Requires-Dist: gymnasium (>=0.28.1,<0.29.0)
Requires-Dist: numpy (>=1.25.1,<2.0.0)
Requires-Dist: pygame (>=2.5.0,<3.0.0)
